dls_servbase_api/__init__.py
dls_servbase_api/aiohttp_client.py
dls_servbase_api/constants.py
dls_servbase_api/exceptions.py
dls_servbase_api/databases/__init__.py
dls_servbase_api/databases/constants.py
dls_servbase_api/databases/database_definition.py
dls_servbase_api/databases/table_definitions.py
dls_servbase_api/datafaces/__init__.py
dls_servbase_api/datafaces/aiohttp.py
dls_servbase_api/datafaces/constants.py
dls_servbase_api/datafaces/context.py
dls_servbase_api/datafaces/datafaces.py
dls_servbase_api/guis/__init__.py
dls_servbase_api/guis/aiohttp.py
dls_servbase_api/guis/constants.py
dls_servbase_api/guis/context.py
dls_servbase_api/guis/guis.py
dls_servbase_cli/__init__.py
dls_servbase_cli/main.py
dls_servbase_cli/version.py
dls_servbase_cli/subcommands/__init__.py
dls_servbase_cli/subcommands/base.py
dls_servbase_cli/subcommands/service.py
dls_servbase_lib/__init__.py
dls_servbase_lib/__main__.py
dls_servbase_lib/_version.py
dls_servbase_lib/base_aiohttp.py
dls_servbase_lib/envvar.py
dls_servbase_lib/version.py
dls_servbase_lib/cookies/__init__.py
dls_servbase_lib/cookies/base.py
dls_servbase_lib/cookies/cookie_parser.py
dls_servbase_lib/cookies/cookies.py
dls_servbase_lib/cookies/dataface.py
dls_servbase_lib/datafaces/__init__.py
dls_servbase_lib/datafaces/aiohttp.py
dls_servbase_lib/datafaces/context.py
dls_servbase_lib/datafaces/datafaces.py
dls_servbase_lib/datafaces/normsql.py
dls_servbase_lib/guis/__init__.py
dls_servbase_lib/guis/aiohttp.py
dls_servbase_lib/guis/base.py
dls_servbase_lib/guis/constants.py
dls_servbase_lib/guis/context.py
dls_servbase_lib/guis/guis.py
dls_servbase_lib/guis/html/index.html
dls_servbase_lib/guis/html/javascript/version.js
dls_servbase-1.7.2.dist-info/LICENSE
dls_servbase-1.7.2.dist-info/METADATA
dls_servbase-1.7.2.dist-info/WHEEL
dls_servbase-1.7.2.dist-info/entry_points.txt
dls_servbase-1.7.2.dist-info/top_level.txt
dls_servbase-1.7.2.dist-info/RECORD
